<?xml version="1.0" standalone="yes"?>
<ATCodes>
	<Code Key="01-66-03" Value="Please use the auto-translate function." />
	<Code Key="01-67-03" Value="Japanese" />
	<Code Key="01-68-03" Value="English" />
	<Code Key="01-69-03" Value="French" />
	<Code Key="01-6A-03" Value="German" />
	<Code Key="01-6B-03" Value="Can you speak Japanese?" />
	<Code Key="01-6C-03" Value="Can you speak English?" />
	<Code Key="01-6D-03" Value="Can you speak French?" />
	<Code Key="01-6E-03" Value="Can you speak German?" />
	<Code Key="01-6F-03" Value="I don't speak any English." />
	<Code Key="01-70-03" Value="I don't speak any Japanese." />
	<Code Key="01-71-03" Value="I don't speak any French." />
	<Code Key="01-72-03" Value="I don't speak any German." />
	<Code Key="01-73-03" Value="Please listen." />
	<Code Key="01-74-03" Value="Can you hear me?" />
	<Code Key="01-75-03" Value="I can speak a little." />
	<Code Key="01-76-03" Value="I can understand a little." />
	<Code Key="01-77-03" Value="Please use simple words." />
	<Code Key="01-78-03" Value="Please do not abbreviate your words." />
	<Code Key="01-79-03" Value="I need some time to put together my answer." />
	<Code Key="02-CA-03" Value="Nice to meet you." />
	<Code Key="02-CB-03" Value="Good morning!" />
	<Code Key="02-CC-03" Value="Hello!" />
	<Code Key="02-CD-03" Value="Good evening!" />
	<Code Key="02-CE-03" Value="Good night!" />
	<Code Key="02-CF-03" Value="Goodbye." />
	<Code Key="02-F0-CF-03" Value="I had fun today!" />
	<Code Key="02-F0-D0-03" Value="See you again!" />
	<Code Key="02-F0-D1-03" Value="Let's play together again sometime!" />
	<Code Key="02-F0-D2-03" Value="I'm back!" />
	<Code Key="02-F0-D3-03" Value="Welcome back." />
	<Code Key="02-F0-D4-03" Value="Congratulations!" />
	<Code Key="02-F0-D5-03" Value="Good job!" />
	<Code Key="02-F0-D6-03" Value="Good luck!" />
	<Code Key="02-F0-D7-03" Value="All right!" />
	<Code Key="02-F0-D8-03" Value="Thank you." />
	<Code Key="02-F0-D9-03" Value="You're welcome." />
	<Code Key="02-F0-DA-03" Value="Take care." />
	<Code Key="02-F0-DB-03" Value="I'm sorry." />
	<Code Key="02-F0-DC-03" Value="Please forgive me." />
	<Code Key="02-F0-DD-03" Value="That's too bad." />
	<Code Key="02-F0-DE-03" Value="Excuse me..." />
	<Code Key="03-F2-01-2D-03" Value="Who?" />
	<Code Key="03-F2-01-2E-03" Value="Which?" />
	<Code Key="03-F2-01-2F-03" Value="How?" />
	<Code Key="03-F2-01-30-03" Value="What?" />
	<Code Key="03-F2-01-31-03" Value="When?" />
	<Code Key="03-F2-01-32-03" Value="How many?" />
	<Code Key="03-F2-01-33-03" Value="Where?" />
	<Code Key="03-F2-01-34-03" Value="Where shall we go?" />
	<Code Key="03-F2-01-35-03" Value="Which guildleve shall we do?" />
	<Code Key="03-F2-01-37-03" Value="Do you have it?" />
	<Code Key="03-F2-01-38-03" Value="What weapons can you use?" />
	<Code Key="03-F2-01-39-03" Value="What guildleves do you have?" />
	<Code Key="03-F2-01-3B-03" Value="Can you do it?" />
	<Code Key="03-F2-01-3C-03" Value="What other classes can you use?" />
	<Code Key="03-F2-01-3D-03" Value="Do you have it set?" />
	<Code Key="03-F2-01-3E-03" Value="What's the battle plan?" />
	<Code Key="03-F2-01-3F-03" Value="What's the Battle Regimen order?" />
	<Code Key="03-F2-01-40-03" Value="Can I add you to my friend list?" />
	<Code Key="03-F2-01-41-03" Value="Shall we take a break?" />
	<Code Key="03-F2-01-42-03" Value="Do you want me to repair it?" />
	<Code Key="03-F2-01-43-03" Value="Do you need any help?" />
	<Code Key="04-F2-01-91-03" Value="I don't understand." />
	<Code Key="04-F2-01-92-03" Value="No thanks." />
	<Code Key="04-F2-01-93-03" Value="Yes, please." />
	<Code Key="04-F2-01-94-03" Value="If you would be so kind." />
	<Code Key="04-F2-01-95-03" Value="Understood." />
	<Code Key="04-F2-01-96-03" Value="I'm sorry. I'm busy now." />
	<Code Key="04-F2-01-97-03" Value="I'm playing solo right now." />
	<Code Key="04-F2-01-98-03" Value="I don't know how ot answer that question." />
	<Code Key="04-F2-01-99-03" Value="I see." />
	<Code Key="04-F2-01-9A-03" Value="Thanks for the offer, but I'll have to pass." />
	<Code Key="04-F2-01-9B-03" Value="That's interesting." />
	<Code Key="04-F2-01-9C-03" Value="Um..." />
	<Code Key="04-F2-01-9D-03" Value="Huh!?" />
	<Code Key="04-F2-01-9E-03" Value="Really?" />
	<Code Key="04-F2-01-9F-03" Value="Hmmm." />
	<Code Key="04-F2-01-A0-03" Value="I have to go soon." />
	<Code Key="05-F2-01-F5-03" Value="Casting spell." />
	<Code Key="05-F2-01-F6-03" Value="Time for work!" />
	<Code Key="05-F2-01-F7-03" Value="I have plans." />
	<Code Key="05-F2-01-F8-03" Value="I'm sleepy." />
	<Code Key="05-F2-01-F9-03" Value="I'm tired." />
	<Code Key="05-F2-01-FA-03" Value="Have stuff to do, gotta go!" />
	<Code Key="05-F2-01-FB-03" Value="I don't feel well." />
	<Code Key="05-F2-01-FC-03" Value="I'm not up for it." />
	<Code Key="05-F2-01-FD-03" Value="I'm interested." />
	<Code Key="05-F2-01-FE-03" Value="Fighting right now!" />
	<Code Key="05-F2-01-FF-03" Value="I want to make money." />
	<Code Key="05-F1-02-03" Value="I don't remember." />
	<Code Key="05-F2-02-01-03" Value="I don't know." />
	<Code Key="05-F2-02-02-03" Value="Just used it." />
	<Code Key="05-F2-02-03-03" Value="I want experience points." />
	<Code Key="05-F2-02-04-03" Value="I want skill points." />
	<Code Key="06-F2-02-59-03" Value="Can I have it?" />
	<Code Key="06-F2-02-5A-03" Value="Can you do it for me?" />
	<Code Key="06-F2-02-5B-03" Value="Lower the price?" />
	<Code Key="06-F2-02-5C-03" Value="Buy?" />
	<Code Key="06-F2-02-5D-03" Value="Sell?" />
	<Code Key="06-F2-02-5E-03" Value="Trade?" />
	<Code Key="06-F2-02-5F-03" Value="Do you need it?" />
	<Code Key="06-F2-02-60-03" Value="Can you make it?" />
	<Code Key="06-F2-02-61-03" Value="Do you have it?" />
	<Code Key="06-F2-02-62-03" Value="Can you repair it?" />
	<Code Key="06-F2-02-63-03" Value="What materials are needed?" />
	<Code Key="06-F2-02-64-03" Value="No money!" />
	<Code Key="06-F2-02-65-03" Value="I don't have anything to give you." />
	<Code Key="06-F2-02-66-03" Value="You can have this." />
	<Code Key="06-F2-02-67-03" Value="Please." />
	<Code Key="06-F2-02-68-03" Value="Reward:" />
	<Code Key="06-F2-02-69-03" Value="Price:" />
	<Code Key="07-F2-02-BD-03" Value="Looking for members." />
	<Code Key="07-F2-02-BE-03" Value="Gather together." />
	<Code Key="07-F2-02-BF-03" Value="Team up?" />
	<Code Key="07-F2-02-C0-03" Value="Are you alone?" />
	<Code Key="07-F2-02-C1-03" Value="Any vacancies?" />
	<Code Key="07-F2-02-C2-03" Value="Please invite me." />
	<Code Key="07-F2-02-C3-03" Value="Please let me join." />
	<Code Key="07-F2-02-C4-03" Value="Who is the leader?" />
	<Code Key="07-F2-02-C5-03" Value="Just for a short time is fine." />
	<Code Key="07-F2-02-C6-03" Value="Our party's full." />
	<Code Key="07-F2-02-C7-03" Value="Please assist." />
	<Code Key="07-F2-02-C8-03" Value="Disbanding party." />
	<Code Key="07-F2-02-C9-03" Value="Taking a break." />
	<Code Key="07-F2-02-CA-03" Value="It's better if physical levels aren't too far apart." />
	<Code Key="07-F2-02-CB-03" Value="It's better if skill levels aren't too far apart." />
	<Code Key="08-F2-03-21-03" Value="Please follow." />
	<Code Key="08-F2-03-22-03" Value="I'll follow you." />
	<Code Key="08-F2-03-23-03" Value="Please check it." />
	<Code Key="08-F2-03-24-03" Value="Found it!" />
	<Code Key="08-F2-03-25-03" Value="Full attack!" />
	<Code Key="08-F2-03-26-03" Value="Pull back." />
	<Code Key="08-F2-03-27-03" Value="Watch out for enemies." />
	<Code Key="08-F2-03-28-03" Value="Defeat this one first!" />
	<Code Key="08-F2-03-29-03" Value="Please don't attack." />
	<Code Key="08-F2-03-2A-03" Value="Please deactivate it." />
	<Code Key="08-F2-03-2B-03" Value="Heal!" />
	<Code Key="08-F2-03-2C-03" Value="Run away!" />
	<Code Key="08-F2-03-2D-03" Value="Help me out!" />
	<Code Key="08-F2-03-2E-03" Value="Stop!" />
	<Code Key="08-F2-03-2F-03" Value="Standing by." />
	<Code Key="08-F2-03-30-03" Value="None left." />
	<Code Key="08-F2-03-31-03" Value="Don't have it." />
	<Code Key="08-F2-03-32-03" Value="Please use it sparingly." />
	<Code Key="08-F2-03-33-03" Value="I'll use it sparingly." />
	<Code Key="08-F2-03-34-03" Value="I'm weakened." />
	<Code Key="08-F2-03-35-03" Value="My gear is in poor condition." />
	<Code Key="08-F2-03-36-03" Value="Ready!" />
	<Code Key="08-F2-03-37-03" Value="Making a Battle Regimen." />
	<Code Key="08-F2-03-38-03" Value="Starting the Battle Regimen." />
	<Code Key="08-F2-03-39-03" Value="Please set enemy marks." />
	<Code Key="08-F2-03-3A-03" Value="Please set an ally mark." />
	<Code Key="08-F2-03-3B-03" Value="Please use it." />
	<Code Key="08-F2-03-3C-03" Value="Let's rest for a while." />
	<Code Key="08-F2-03-3D-03" Value="Front line job" />
	<Code Key="08-F2-03-3E-03" Value="Support role job" />
	<Code Key="08-F2-03-3F-03" Value="Back line job" />
	<Code Key="08-F2-03-40-03" Value="Weakness" />
	<Code Key="08-F2-03-41-03" Value="Warning" />
	<Code Key="08-F2-03-42-03" Value="Recommend" />
	<Code Key="08-F2-03-43-03" Value="Kill Order" />
	<Code Key="09-F2-03-85-03" Value="Guildleve" />
	<Code Key="09-F2-03-87-03" Value="Quest" />
	<Code Key="09-F2-03-88-03" Value="Client" />
	<Code Key="09-F2-03-89-03" Value="Instance" />
	<Code Key="09-F2-03-8A-03" Value="Gil" />
	<Code Key="09-F2-03-8B-03" Value="Skill" />
	<Code Key="09-F2-03-8C-03" Value="Primary Skill" />
	<Code Key="09-F2-03-8D-03" Value="Primary Skill Rank" />
	<Code Key="09-F2-03-8E-03" Value="Physical Level" />
	<Code Key="09-F2-03-8F-03" Value="Skill Point" />
	<Code Key="09-F2-03-90-03" Value="Experience Points" />
	<Code Key="09-F2-03-91-03" Value="Affinity" />
	<Code Key="09-F2-03-92-03" Value="Attribute" />
	<Code Key="09-F2-03-93-03" Value="Elemental Resistance" />
	<Code Key="09-F2-03-94-03" Value="Fire" />
	<Code Key="09-F2-03-95-03" Value="Ice" />
	<Code Key="09-F2-03-96-03" Value="Wind" />
	<Code Key="09-F2-03-97-03" Value="Earth" />
	<Code Key="09-F2-03-98-03" Value="Lightning" />
	<Code Key="09-F2-03-99-03" Value="Water" />
	<Code Key="09-F2-03-9A-03" Value="Astral" />
	<Code Key="09-F2-03-9B-03" Value="Umbral" />
	<Code Key="09-F2-03-9C-03" Value="Guardian" />
	<Code Key="09-F2-03-9D-03" Value="Nameday" />
	<Code Key="09-F2-03-9E-03" Value="Race" />
	<Code Key="09-F2-03-9F-03" Value="Clan" />
	<Code Key="09-F2-03-A0-03" Value="Gender" />
	<Code Key="09-F2-03-A1-03" Value="Title" />
	<Code Key="09-F2-03-A2-03" Value="Quality" />
	<Code Key="09-F2-03-A3-03" Value="???" />
	<Code Key="09-F2-03-A4-03" Value="??" />
	<Code Key="09-F2-03-A5-03" Value="?" />
	<Code Key="09-F2-03-A6-03" Value="Durability" />
	<Code Key="09-F2-03-AC-03" Value="To Repair" />
	<Code Key="09-F2-03-AD-03" Value="Status Effect" />
	<Code Key="09-F2-03-AE-03" Value="Cast Time" />
	<Code Key="09-F2-03-AF-03" Value="Recast Time" />
	<Code Key="09-F2-03-B0-03" Value="KO'd" />
	<Code Key="09-F2-03-B1-03" Value="Craft" />
	<Code Key="09-F2-03-B2-03" Value="Gathering" />
	<Code Key="09-F2-03-B3-03" Value="Negotiate" />
	<Code Key="09-F2-03-B4-03" Value="Guild Mark" />
	<Code Key="09-F2-03-B5-03" Value="Mark" />
	<Code Key="09-F2-03-B6-03" Value="Linkshell" />
	<Code Key="09-F2-03-B7-03" Value="Linkpearl" />
	<Code Key="09-F2-03-B8-03" Value="Active Mode" />
	<Code Key="09-F2-03-B9-03" Value="Passive Mode" />
	<Code Key="09-F2-03-BA-03" Value="Action" />
	<Code Key="09-F2-03-BB-03" Value="Magic" />
	<Code Key="09-F2-03-BC-03" Value="Weaponskill" />
	<Code Key="09-F2-03-BD-03" Value="Ability" />
	<Code Key="09-F2-03-BE-03" Value="Trait" />
	<Code Key="09-F2-03-BF-03" Value="Gathering Actions" />
	<Code Key="09-F2-03-C0-03" Value="Synthesis Actions" />
	<Code Key="09-F2-03-C1-03" Value="Engage" />
	<Code Key="09-F2-03-C2-03" Value="Disengage" />
	<Code Key="09-F2-03-C3-03" Value="Incapacitated" />
	<Code Key="09-F2-03-C4-03" Value="Battle Regimen" />
	<Code Key="09-F2-03-C5-03" Value="Enmity" />
	<Code Key="09-F2-03-C6-03" Value="Loot" />
	<Code Key="09-F2-03-C7-03" Value="Enemy Sign" />
	<Code Key="09-F2-03-C8-03" Value="Ally Sign" />
	<Code Key="09-F2-03-C9-03" Value="Target" />
	<Code Key="09-F2-03-CA-03" Value="(Gear) Affinity" />
	<Code Key="09-F2-03-CB-03" Value="Rare" />
	<Code Key="09-F2-03-CC-03" Value="Unique" />
	<Code Key="09-F2-03-CD-03" Value="Party" />
	<Code Key="09-F2-03-CE-03" Value="Map" />
	<Code Key="09-F2-03-CF-03" Value="Log out" />
	<Code Key="09-F2-03-D0-03" Value="Indent" />
	<Code Key="09-F2-03-D1-03" Value="Pattern" />
	<Code Key="09-F2-03-D2-03" Value="Retainer" />
	<Code Key="09-F2-03-D3-03" Value="Chocobo" />
	<Code Key="09-F2-03-D4-03" Value="Aetheryte" />
	<Code Key="09-F2-03-D5-03" Value="Aetherial Gate" />
	<Code Key="09-F2-03-D6-03" Value="Aetherial Node" />
	<Code Key="09-F2-03-D7-03" Value="Trade" />
	<Code Key="09-F2-03-D8-03" Value="Bazaar" />
	<Code Key="09-F2-03-D9-03" Value="Repair" />
	<Code Key="09-F2-03-DA-03" Value="Auto-translation Dictionary" />
	<Code Key="09-F2-03-DB-03" Value="Teleport" />
	<Code Key="09-F2-03-DC-03" Value="Warp" />
	<Code Key="09-F2-03-DD-03" Value="Guild Shop" />
	<Code Key="09-F2-03-DE-03" Value="Hyur" />
	<Code Key="09-F2-03-DF-03" Value="Elezen" />
	<Code Key="09-F2-03-E0-03" Value="Lalafell" />
	<Code Key="09-F2-03-E1-03" Value="Miqo'te" />
	<Code Key="09-F2-03-E2-03" Value="Roegadyn" />
	<Code Key="09-F2-03-E3-03" Value="Midlander" />
	<Code Key="09-F2-03-E4-03" Value="Highlander" />
	<Code Key="09-F2-03-E5-03" Value="Wildwood" />
	<Code Key="09-F2-03-E6-03" Value="Duskwight" />
	<Code Key="09-F2-03-E7-03" Value="Plainsfolk" />
	<Code Key="09-F2-03-E8-03" Value="Dunesfolk" />
	<Code Key="09-F2-03-E9-03" Value="Seeker of the Sun" />
	<Code Key="09-F2-03-EA-03" Value="Keeper of the Moon" />
	<Code Key="09-F2-03-EB-03" Value="Sea Wolf" />
	<Code Key="09-F2-03-EC-03" Value="Hellsguard" />
	<Code Key="09-F2-03-ED-03" Value="Diciples of War" />
	<Code Key="09-F2-03-EE-03" Value="Disciples of Magic" />
	<Code Key="09-F2-03-EF-03" Value="Disciples of the Land" />
	<Code Key="09-F2-03-F0-03" Value="Disciples of the Hand" />
	<Code Key="0A-F2-04-B1-03" Value="/?" />
	<Code Key="0A-F2-04-B2-03" Value="/action" />
	<Code Key="0A-F2-04-B3-03" Value="/angry" />
	<Code Key="0A-F2-04-B4-03" Value="/areaofeffect" />
	<Code Key="0A-F2-04-B5-03" Value="/automove" />
	<Code Key="0A-F2-04-B6-03" Value="/away" />
	<Code Key="0A-F2-04-B7-03" Value="/battlemode" />
	<Code Key="0A-F2-04-B8-03" Value="/battleregimen" />
	<Code Key="0A-F2-04-B9-03" Value="/beckon" />
	<Code Key="0A-F2-04-BA-03" Value="/blacklist" />
	<Code Key="0A-F2-04-BB-03" Value="/blush" />
	<Code Key="0A-F2-04-BC-03" Value="/bow" />
	<Code Key="0A-F2-04-BE-03" Value="/chatmode" />
	<Code Key="0A-F2-04-BF-03" Value="/check" />
	<Code Key="0A-F2-04-C0-03" Value="/cheer" />
	<Code Key="0A-F2-04-C1-03" Value="/chuckle" />
	<Code Key="0A-F2-04-C2-03" Value="/clap" />
	<Code Key="0A-F2-04-C3-03" Value="/clock" />
	<Code Key="0A-F2-04-C4-03" Value="/comfort" />
	<Code Key="0A-F2-04-C6-03" Value="/congratulate" />
	<Code Key="0A-F2-04-C7-03" Value="/cry" />
	<Code Key="0A-F2-04-C8-03" Value="/dance" />
	<Code Key="0A-F2-04-C9-03" Value="/decline" />
	<Code Key="0A-F2-04-CA-03" Value="/deny" />
	<Code Key="0A-F2-04-CD-03" Value="/display" />
	<Code Key="0A-F2-04-CB-03" Value="/doubt" />
	<Code Key="0A-F2-04-CC-03" Value="/doze" />
	<Code Key="0A-F2-04-CE-03" Value="/dusteffect" />
	<Code Key="0A-F2-04-CF-03" Value="/echo" />
	<Code Key="0A-F2-04-D0-03" Value="/emote" />
	<Code Key="0A-F2-04-D1-03" Value="/equip" />
	<Code Key="0A-F2-04-D2-03" Value="/equipaction" />
	<Code Key="0A-F2-04-D3-03" Value="/examineself" />
	<Code Key="0A-F2-04-D4-03" Value="/extendeddraw" />
	<Code Key="0A-F2-04-D6-03" Value="/friendlist" />
	<Code Key="0A-F2-04-D7-03" Value="/fume" />
	<Code Key="0A-F2-04-D8-03" Value="/furious" />
	<Code Key="0A-F2-04-D9-03" Value="/goodbye" />
	<Code Key="0A-F2-04-DB-03" Value="/item" />
	<Code Key="0A-F2-04-DC-03" Value="/join" />
	<Code Key="0A-F2-04-DD-03" Value="/joy" />
	<Code Key="0A-F2-04-DE-03" Value="/kneel" />
	<Code Key="0A-F2-04-DF-03" Value="/laugh" />
	<Code Key="0A-F2-04-E0-03" Value="/linkshell" />
	<Code Key="0A-F2-04-E2-03" Value="/lockon" />
	<Code Key="0A-F2-04-E3-03" Value="/logout" />
	<Code Key="0A-F2-04-E4-03" Value="/lookout" />
	<Code Key="0A-F2-04-E5-03" Value="/loot" />
	<Code Key="0A-F2-04-E7-03" Value="/map" />
	<Code Key="0A-F2-04-E8-03" Value="/marking" />
	<Code Key="0A-F2-04-E9-03" Value="/me" />
	<Code Key="0A-F2-04-EA-03" Value="/meh" />
	<Code Key="0A-F2-04-EB-03" Value="/names" />
	<Code Key="0A-F2-04-EC-03" Value="/no" />
	<Code Key="0A-F2-04-EE-03" Value="/panic" />
	<Code Key="0A-F2-04-EF-03" Value="/party" />
	<Code Key="0A-F2-04-F0-03" Value="/partycmd" />
	<Code Key="0A-F2-04-F1-03" Value="/physics" />
	<Code Key="0A-F2-04-F3-03" Value="/point" />
	<Code Key="0A-F2-04-F4-03" Value="/poke" />
	<Code Key="0A-F2-04-F5-03" Value="/profanity" />
	<Code Key="0A-F2-04-F6-03" Value="/psych" />
	<Code Key="0A-F2-04-F7-03" Value="/rally" />
	<Code Key="0A-F2-04-F8-03" Value="/recast" />
	<Code Key="0A-F2-04-F9-03" Value="/salute" />
	<Code Key="0A-F2-04-FA-03" Value="/say" />
	<Code Key="0A-F2-04-FB-03" Value="/scrollingbattletext" />
	<Code Key="0A-F2-04-FD-03" Value="/shadow" />
	<Code Key="0A-F2-04-FE-03" Value="/shocked" />
	<Code Key="0A-F2-04-FF-03" Value="/shout" />
	<Code Key="0A-F1-05-03" Value="/shrug" />
	<Code Key="0A-F2-05-01-03" Value="/sit" />
	<Code Key="0A-F2-05-02-03" Value="/soothe" />
	<Code Key="0A-F2-05-03-03" Value="/stagger" />
	<Code Key="0A-F2-05-04-03" Value="/stretch" />
	<Code Key="0A-F2-05-05-03" Value="/sulk" />
	<Code Key="0A-F2-05-06-03" Value="/supportdesk" />
	<Code Key="0A-F2-05-07-03" Value="/surprised" />
	<Code Key="0A-F2-05-09-03" Value="/targetnpc" />
	<Code Key="0A-F2-05-0A-03" Value="/targetpc" />
	<Code Key="0A-F2-05-0B-03" Value="/tell" />
	<Code Key="0A-F2-05-15-03" Value="/textclear" />
	<Code Key="0A-F2-05-0C-03" Value="/think" />
	<Code Key="0A-F2-05-0D-03" Value="/thumbsup" />
	<Code Key="0A-F2-05-0E-03" Value="/upset" />
	<Code Key="0A-F2-05-10-03" Value="/wait" />
	<Code Key="0A-F2-05-11-03" Value="/wave" />
	<Code Key="0A-F2-05-12-03" Value="/welcome" />
	<Code Key="0A-F2-05-14-03" Value="/yes" />
	<Code Key="0B-F2-05-DD-03" Value="North" />
	<Code Key="0B-F2-05-DE-03" Value="South" />
	<Code Key="0B-F2-05-DF-03" Value="East" />
	<Code Key="0B-F2-05-E0-03" Value="West" />
	<Code Key="0B-F2-05-E1-03" Value="Up" />
	<Code Key="0B-F2-05-E2-03" Value="Down" />
	<Code Key="0B-F2-05-E3-03" Value="Right" />
	<Code Key="0B-F2-05-E4-03" Value="Left" />
	<Code Key="0B-F2-05-E5-03" Value="Surface" />
	<Code Key="0B-F2-05-E6-03" Value="Rear" />
	<Code Key="0B-F2-05-E7-03" Value="Side" />
	<Code Key="0B-F2-05-E8-03" Value="Front" />
	<Code Key="0B-F2-05-E9-03" Value="Middle" />
	<Code Key="0B-F2-05-EA-03" Value="Flank" />
	<Code Key="0B-F2-05-EB-03" Value="Inside" />
	<Code Key="0B-F2-05-EC-03" Value="Outside" />
	<Code Key="0B-F2-05-ED-03" Value="This way" />
	<Code Key="0B-F2-05-EE-03" Value="Over there" />
	<Code Key="0B-F2-05-EF-03" Value="That way" />
	<Code Key="0C-F2-06-41-03" Value="Day before yesterday" />
	<Code Key="0C-F2-06-42-03" Value="Yesterday" />
	<Code Key="0C-F2-06-43-03" Value="Today" />
	<Code Key="0C-F2-06-44-03" Value="Tomorrow" />
	<Code Key="0C-F2-06-45-03" Value="Day after tomorrow" />
	<Code Key="0C-F2-06-46-03" Value="Last week" />
	<Code Key="0C-F2-06-47-03" Value="This week" />
	<Code Key="0C-F2-06-48-03" Value="Next week" />
	<Code Key="0C-F2-06-49-03" Value="a.m." />
	<Code Key="0C-F2-06-4A-03" Value="p.m." />
	<Code Key="0C-F2-06-4B-03" Value="Morning" />
	<Code Key="0C-F2-06-4C-03" Value="Afternoon" />
	<Code Key="0C-F2-06-4D-03" Value="Night" />
	<Code Key="0C-F2-06-4E-03" Value="Day of the week" />
	<Code Key="0C-F2-06-4F-03" Value="Sunday" />
	<Code Key="0C-F2-06-50-03" Value="Monday" />
	<Code Key="0C-F2-06-51-03" Value="Tuesday" />
	<Code Key="0C-F2-06-52-03" Value="Wednesday" />
	<Code Key="0C-F2-06-53-03" Value="Thursday" />
	<Code Key="0C-F2-06-54-03" Value="Friday" />
	<Code Key="0C-F2-06-55-03" Value="Saturday" />
	<Code Key="0C-F2-06-56-03" Value="Holiday" />
	<Code Key="0C-F2-06-57-03" Value="Break" />
	<Code Key="0C-F2-06-5A-03" Value="Second" />
	<Code Key="0C-F2-06-58-03" Value="Long time" />
	<Code Key="0C-F2-06-59-03" Value="Short time" />
	<Code Key="0C-F2-06-5B-03" Value="Minute" />
	<Code Key="0C-F2-06-5C-03" Value="Hour" />
	<Code Key="0C-F2-06-5D-03" Value="Time remaining" />
	<Code Key="0C-F2-06-5E-03" Value="January" />
	<Code Key="0C-F2-06-5F-03" Value="February" />
	<Code Key="0C-F2-06-60-03" Value="March (Month)" />
	<Code Key="0C-F2-06-61-03" Value="April" />
	<Code Key="0C-F2-06-62-03" Value="May" />
	<Code Key="0C-F2-06-63-03" Value="June" />
	<Code Key="0C-F2-06-64-03" Value="July" />
	<Code Key="0C-F2-06-65-03" Value="August" />
	<Code Key="0C-F2-06-66-03" Value="September" />
	<Code Key="0C-F2-06-67-03" Value="October" />
	<Code Key="0C-F2-06-68-03" Value="November" />
	<Code Key="0C-F2-06-69-03" Value="December" />
	<Code Key="0D-F2-06-A5-03" Value="Connection Speed" />
	<Code Key="0D-F2-06-A6-03" Value="Blacklist" />
	<Code Key="0D-F2-06-A7-03" Value="Friend List" />
	<Code Key="0D-F2-06-A8-03" Value="Config" />
	<Code Key="0D-F2-06-A9-03" Value="Connection" />
	<Code Key="0D-F2-06-AA-03" Value="Screenshot" />
	<Code Key="0D-F2-06-AB-03" Value="Patch" />
	<Code Key="0D-F2-06-AC-03" Value="Version" />
	<Code Key="0D-F2-06-AD-03" Value="Connection Lost" />
	<Code Key="0D-F2-06-AE-03" Value="Lag" />
	<Code Key="0D-F2-06-AF-03" Value="Filter" />
	<Code Key="0D-F2-06-B0-03" Value="Client" />
	<Code Key="0D-F2-06-B1-03" Value="Backup" />
	<Code Key="0D-F2-06-B3-03" Value="Save" />
	<Code Key="0D-F2-06-B4-03" Value="TV" />
	<Code Key="0D-F2-06-B5-03" Value="Modem" />
	<Code Key="0D-F2-06-B6-03" Value="Monitor" />
	<Code Key="0D-F2-06-B7-03" Value="Log off" />
	<Code Key="0D-F2-06-B8-03" Value="Log on" />
	<Code Key="0D-F2-06-B9-03" Value="Hard Disk" />
	<Code Key="0D-F2-06-BA-03" Value="Server" />
	<Code Key="0D-F2-06-BB-03" Value="Macro" />
	<Code Key="0E-F2-07-09-03" Value="Online" />
	<Code Key="0E-F2-07-0A-03" Value="Away" />
	<Code Key="0F-F2-07-6D-03" Value="Numeric keypad" />
	<Code Key="0F-F2-07-6E-03" Value="Arrow keys" />
	<Code Key="0F-F2-07-6F-03" Value="Tab key" />
	<Code Key="0F-F2-07-70-03" Value="Enter key" />
	<Code Key="0F-F2-07-71-03" Value="End key" />
	<Code Key="0F-F2-07-72-03" Value="Num Lock key" />
	<Code Key="0F-F2-07-73-03" Value="Function keys" />
	<Code Key="0F-F2-07-74-03" Value="Spacebar" />
	<Code Key="0F-F2-07-75-03" Value="Backspace key" />
	<Code Key="0F-F2-07-76-03" Value="Halfwidth/Fullwidth key" />
	<Code Key="0F-F2-07-77-03" Value="Alt key" />
	<Code Key="0F-F2-07-78-03" Value="Insert key" />
	<Code Key="0F-F2-07-79-03" Value="Page Down key" />
	<Code Key="0F-F2-07-7A-03" Value="Home key" />
	<Code Key="0F-F2-07-7B-03" Value="Page Up key" />
	<Code Key="0F-F2-07-7C-03" Value="Caps Lock key" />
	<Code Key="0F-F2-07-7D-03" Value="Shift key" />
	<Code Key="0F-F2-07-7E-03" Value="Esc key" />
	<Code Key="0F-F2-07-7F-03" Value="Ctrl key" />
	<Code Key="0F-F2-07-80-03" Value="Delete key" />
	<Code Key="10-F2-07-D1-03" Value="notice" />
	<Code Key="10-F2-07-D2-03" Value="place" />
	<Code Key="10-F2-07-D3-03" Value="meat" />
	<Code Key="10-F2-07-D4-03" Value="train" />
	<Code Key="10-F2-07-D5-03" Value="last" />
	<Code Key="10-F2-07-D7-03" Value="question" />
	<Code Key="10-F2-07-D6-03" Value="death" />
	<Code Key="10-F2-07-D8-03" Value="joy" />
	<Code Key="10-F2-07-D9-03" Value="mistake" />
	<Code Key="10-F2-07-DA-03" Value="purpose" />
	<Code Key="10-F2-07-DB-03" Value="half" />
	<Code Key="10-F2-07-DC-03" Value="date" />
	<Code Key="10-F2-07-DD-03" Value="secret" />
	<Code Key="10-F2-07-DE-03" Value="position" />
	<Code Key="10-F2-07-DF-03" Value="lie" />
	<Code Key="10-F2-07-E0-03" Value="excitement" />
	<Code Key="10-F2-07-E1-03" Value="money" />
	<Code Key="10-F2-07-E2-03" Value="fear" />
	<Code Key="10-F2-07-E3-03" Value="friend" />
	<Code Key="10-F2-07-E4-03" Value="entrance" />
	<Code Key="10-F2-07-E5-03" Value="exit" />
	<Code Key="10-F2-07-E6-03" Value="mine" />
	<Code Key="10-F2-07-E7-03" Value="fun" />
	<Code Key="10-F2-07-E8-03" Value="I" />
	<Code Key="10-F2-07-E9-03" Value="you" />
	<Code Key="11-02-03" Value="Halone, the Fury" />
	<Code Key="11-03-03" Value="Menphina, the Lover" />
	<Code Key="11-04-03" Value="Thaliak, the Scholar" />
	<Code Key="11-05-03" Value="Nymeia, the Spinner" />
	<Code Key="11-06-03" Value="Llymlaen, the Navigator" />
	<Code Key="11-07-03" Value="Oschon, the Wanderer" />
	<Code Key="11-08-03" Value="Byregot, the Builder" />
	<Code Key="11-09-03" Value="Rhalgr, the Destroyer" />
	<Code Key="11-0A-03" Value="Azeyma, the Warden" />
	<Code Key="11-0B-03" Value="Nald'thal, the Traders" />
	<Code Key="11-0C-03" Value="Nophica, the Matron" />
	<Code Key="11-0D-03" Value="Althyk, the Keeper" />
	<Code Key="12-02-03" Value="Main hand" />
	<Code Key="12-03-03" Value="Off Hand" />
	<Code Key="12-06-03" Value="Throwing Weapon" />
	<Code Key="12-07-03" Value="Pack" />
	<Code Key="12-08-03" Value="Pouch" />
	<Code Key="12-0A-03" Value="Head" />
	<Code Key="12-0B-03" Value="Undershirt" />
	<Code Key="12-0C-03" Value="Body" />
	<Code Key="12-0D-03" Value="Undergarment" />
	<Code Key="12-0E-03" Value="Legs" />
	<Code Key="12-0F-03" Value="Hands" />
	<Code Key="12-10-03" Value="Feet" />
	<Code Key="12-11-03" Value="Waist" />
	<Code Key="12-12-03" Value="Neck" />
	<Code Key="12-13-03" Value="Right Ear" />
	<Code Key="12-14-03" Value="Left Ear" />
	<Code Key="12-15-03" Value="Right Wrist" />
	<Code Key="12-16-03" Value="Left Wrist" />
	<Code Key="12-17-03" Value="Right Index Finger" />
	<Code Key="12-18-03" Value="Left Index Finger" />
	<Code Key="12-19-03" Value="Right Ring Finger" />
	<Code Key="12-20-03" Value="Left Ring Finger" />
	<Code Key="13-03-03" Value="Hand-to-Hand" />
	<Code Key="13-04-03" Value="Sword" />
	<Code Key="13-05-03" Value="Axe" />
	<Code Key="13-08-03" Value="Archery" />
	<Code Key="13-09-03" Value="Polearm" />
	<Code Key="13-0B-03" Value="Shield" />
	<Code Key="13-17-03" Value="Thaumaturgy" />
	<Code Key="13-18-03" Value="Conjury" />
	<Code Key="13-1E-03" Value="Woodworking" />
	<Code Key="13-1F-03" Value="Smithing" />
	<Code Key="13-20-03" Value="Armorcraft" />
	<Code Key="13-21-03" Value="Goldsmithing" />
	<Code Key="13-22-03" Value="Leatherworking" />
	<Code Key="13-23-03" Value="Clothcraft" />
	<Code Key="13-24-03" Value="Alchemy" />
	<Code Key="13-25-03" Value="Cooking" />
	<Code Key="13-28-03" Value="Mining" />
	<Code Key="13-29-03" Value="Botany" />
	<Code Key="13-2A-03" Value="Fishing" />
	<Code Key="14-03-03" Value="Pugilist" />
	<Code Key="14-04-03" Value="Gladiator" />
	<Code Key="14-05-03" Value="Marauder" />
	<Code Key="14-08-03" Value="Archer" />
	<Code Key="14-09-03" Value="Lancer" />
	<Code Key="14-17-03" Value="Thaumaturge" />
	<Code Key="14-18-03" Value="Conjurer" />
	<Code Key="14-1E-03" Value="Carpenter" />
	<Code Key="14-1F-03" Value="Blacksmith" />
	<Code Key="14-20-03" Value="Armorer" />
	<Code Key="14-21-03" Value="Goldsmith" />
	<Code Key="14-22-03" Value="Leatherworker" />
	<Code Key="14-23-03" Value="Weaver" />
	<Code Key="14-24-03" Value="Alchemist" />
	<Code Key="14-25-03" Value="Culinarian" />
	<Code Key="14-28-03" Value="Miner" />
	<Code Key="14-29-03" Value="Botanist" />
	<Code Key="14-2A-03" Value="Fisher" />
</ATCodes>